INFINITE_CONTEXT_WINDOW/INFINITE_CONTEXT_WINDOW.py
INFINITE_CONTEXT_WINDOW/__init__.py
INFINITE_CONTEXT_WINDOW/allowed_extensions.py
infinite_context_window-3.0.2.dist-info/LICENSE.txt
infinite_context_window-3.0.2.dist-info/METADATA
infinite_context_window-3.0.2.dist-info/WHEEL
infinite_context_window-3.0.2.dist-info/top_level.txt
infinite_context_window-3.0.2.dist-info/RECORD
