Metadata-Version: 2.2
Name: INFINITE_CONTEXT_WINDOW
Version: 3.0.2
Home-page: https://github.com/sapiens-technology/INFINITE_CONTEXT_WINDOW
Author: SAPIENS TECHNOLOGY
License: Proprietary Software
License-File: LICENSE.txt
Requires-Dist: TTS==0.22.0
Requires-Dist: paddlepaddle
Requires-Dist: utilities-nlp
Requires-Dist: perpetual-context-window
Requires-Dist: infinite-context
Requires-Dist: perpetual-context
Dynamic: author
Dynamic: home-page
Dynamic: license
Dynamic: requires-dist
